waifu_pypics/__init__.py
waifu_pypics/async_client.py
waifu_pypics/client.py
waifu_pypics/errors.py
waifu_pypics-1.0.2.dist-info/METADATA
waifu_pypics-1.0.2.dist-info/WHEEL
waifu_pypics-1.0.2.dist-info/top_level.txt
waifu_pypics-1.0.2.dist-info/RECORD
