Metadata-Version: 2.1
Name: waifu-pypics
Version: 1.0.2
Summary: A Python wrapper for Waifu-Pics Api
Home-page: https://github.com/This-is-not-Reidy/Waifu-Pypics.git
Author: Reidy
License: UNKNOWN
Project-URL: Author Discord, https://discord.com/users/848593011038224405
Platform: UNKNOWN
Requires-Dist: aiohttp
Requires-Dist: requests
Requires-Dist: asyncio
